biomage_programmatic_interface/__init__.py
biomage_programmatic_interface/connection.py
biomage_programmatic_interface/exceptions.py
biomage_programmatic_interface/experiment.py
biomage_programmatic_interface/objectS3.py
biomage_programmatic_interface/sample.py
biomage_programmatic_interface/sample_file.py
biomage_programmatic_interface/utils.py
biomage_programmatic_interface-0.0.39.dist-info/LICENSE
biomage_programmatic_interface-0.0.39.dist-info/METADATA
biomage_programmatic_interface-0.0.39.dist-info/WHEEL
biomage_programmatic_interface-0.0.39.dist-info/top_level.txt
biomage_programmatic_interface-0.0.39.dist-info/RECORD
