Metadata-Version: 2.1
Name: biomage-programmatic-interface
Version: 0.0.39
Summary: For programmatic upload of files to Cellencis
Home-page: https://github.com/biomage-org/programmatic_interface
Author: Biomage Ltd
Author-email: engineering@biomage.net
Keywords: pypi,cicd,python
Classifier: Programming Language :: Python :: 3
Classifier: Operating System :: OS Independent
Classifier: License :: OSI Approved :: MIT License
License-File: LICENSE
